{
  "env": "halfcheetah-medium-v2",
  "method": "disentangled_dcor_reward_only",
  "seed": 3,
  "noise_dim": 17,
  "noise_scale": 0.5,
  "noise_type": "nonlinear",
  "avg_return": 1328.350752186064,
  "std_return": 723.1460621742306,
  "normalized_score": 12.956154005314433,
  "latent_dim": 25,
  "pretrain_epochs": 50,
  "iql_epochs": 100,
  "encoder_checkpoint": "/workspace/robust-offline-rl-disentanglement/artifacts/checkpoints/disentangled_dcor_reward_only/halfcheetah-medium-v2/nd17_ns0p5_nonlinear/seed_3/encoder_epoch_50.pth",
  "obs_stats_path": "/workspace/robust-offline-rl-disentanglement/artifacts/obs_stats/disentangled_dcor_reward_only/halfcheetah-medium-v2/nd17_ns0p5_nonlinear/seed_3/obs_stats.npz",
  "iql_history": [
    {
      "epoch": 1,
      "value_loss": 0.10270041972398758,
      "q_loss": 9.664762496948242,
      "actor_loss": 3.9251060485839844
    },
    {
      "epoch": 2,
      "value_loss": 0.5429456233978271,
      "q_loss": 40.680938720703125,
      "actor_loss": 2.667968273162842
    },
    {
      "epoch": 3,
      "value_loss": 0.9566565752029419,
      "q_loss": 83.67577362060547,
      "actor_loss": 2.071251153945923
    },
    {
      "epoch": 4,
      "value_loss": 1.111617088317871,
      "q_loss": 126.90927124023438,
      "actor_loss": 1.6681599617004395
    },
    {
      "epoch": 5,
      "value_loss": 1.0725955963134766,
      "q_loss": 165.0463104248047,
      "actor_loss": 1.3958035707473755
    },
    {
      "epoch": 6,
      "value_loss": 0.9171485900878906,
      "q_loss": 198.8328857421875,
      "actor_loss": 1.1647886037826538
    },
    {
      "epoch": 7,
      "value_loss": 0.7183213233947754,
      "q_loss": 227.82652282714844,
      "actor_loss": 0.9732065796852112
    },
    {
      "epoch": 8,
      "value_loss": 0.5726332664489746,
      "q_loss": 252.59596252441406,
      "actor_loss": 0.8073340654373169
    },
    {
      "epoch": 9,
      "value_loss": 0.45977312326431274,
      "q_loss": 273.52520751953125,
      "actor_loss": 0.6659683585166931
    },
    {
      "epoch": 10,
      "value_loss": 0.38996589183807373,
      "q_loss": 291.82470703125,
      "actor_loss": 0.5537100434303284
    },
    {
      "epoch": 11,
      "value_loss": 0.32824379205703735,
      "q_loss": 305.8345642089844,
      "actor_loss": 0.455152690410614
    },
    {
      "epoch": 12,
      "value_loss": 0.27992239594459534,
      "q_loss": 318.532470703125,
      "actor_loss": 0.36242395639419556
    },
    {
      "epoch": 13,
      "value_loss": 0.25425341725349426,
      "q_loss": 329.5089111328125,
      "actor_loss": 0.2725192606449127
    },
    {
      "epoch": 14,
      "value_loss": 0.23181189596652985,
      "q_loss": 338.2372131347656,
      "actor_loss": 0.20134484767913818
    },
    {
      "epoch": 15,
      "value_loss": 0.21445134282112122,
      "q_loss": 345.540771484375,
      "actor_loss": 0.1315174549818039
    },
    {
      "epoch": 16,
      "value_loss": 0.20230570435523987,
      "q_loss": 350.4017028808594,
      "actor_loss": 0.06638987362384796
    },
    {
      "epoch": 17,
      "value_loss": 0.19053229689598083,
      "q_loss": 356.3112487792969,
      "actor_loss": 0.013877801597118378
    },
    {
      "epoch": 18,
      "value_loss": 0.183505117893219,
      "q_loss": 360.08856201171875,
      "actor_loss": -0.03864605352282524
    },
    {
      "epoch": 19,
      "value_loss": 0.1667868047952652,
      "q_loss": 362.6104736328125,
      "actor_loss": -0.08097447454929352
    },
    {
      "epoch": 20,
      "value_loss": 0.16626425087451935,
      "q_loss": 366.4531555175781,
      "actor_loss": -0.12441882491111755
    },
    {
      "epoch": 21,
      "value_loss": 0.15656182169914246,
      "q_loss": 368.8175964355469,
      "actor_loss": -0.1710227131843567
    },
    {
      "epoch": 22,
      "value_loss": 0.15277618169784546,
      "q_loss": 370.530517578125,
      "actor_loss": -0.20529688894748688
    },
    {
      "epoch": 23,
      "value_loss": 0.1478589028120041,
      "q_loss": 371.9956359863281,
      "actor_loss": -0.23186375200748444
    },
    {
      "epoch": 24,
      "value_loss": 0.14950139820575714,
      "q_loss": 373.8418273925781,
      "actor_loss": -0.26812422275543213
    },
    {
      "epoch": 25,
      "value_loss": 0.13913989067077637,
      "q_loss": 374.3785705566406,
      "actor_loss": -0.29753199219703674
    },
    {
      "epoch": 26,
      "value_loss": 0.14148294925689697,
      "q_loss": 375.750244140625,
      "actor_loss": -0.3243981897830963
    },
    {
      "epoch": 27,
      "value_loss": 0.12849067151546478,
      "q_loss": 376.46490478515625,
      "actor_loss": -0.3519321382045746
    },
    {
      "epoch": 28,
      "value_loss": 0.13212850689888,
      "q_loss": 376.8224182128906,
      "actor_loss": -0.3723139762878418
    },
    {
      "epoch": 29,
      "value_loss": 0.1314578801393509,
      "q_loss": 377.77392578125,
      "actor_loss": -0.40209776163101196
    },
    {
      "epoch": 30,
      "value_loss": 0.1181856244802475,
      "q_loss": 377.9096374511719,
      "actor_loss": -0.4191756844520569
    },
    {
      "epoch": 31,
      "value_loss": 0.12093956768512726,
      "q_loss": 378.43988037109375,
      "actor_loss": -0.442430704832077
    },
    {
      "epoch": 32,
      "value_loss": 0.1206250935792923,
      "q_loss": 378.9320983886719,
      "actor_loss": -0.45347467064857483
    },
    {
      "epoch": 33,
      "value_loss": 0.11206427961587906,
      "q_loss": 379.4269714355469,
      "actor_loss": -0.4806486666202545
    },
    {
      "epoch": 34,
      "value_loss": 0.11940189450979233,
      "q_loss": 379.8982238769531,
      "actor_loss": -0.49442487955093384
    },
    {
      "epoch": 35,
      "value_loss": 0.108426034450531,
      "q_loss": 379.5689392089844,
      "actor_loss": -0.5113296508789062
    },
    {
      "epoch": 36,
      "value_loss": 0.1055200919508934,
      "q_loss": 379.8587341308594,
      "actor_loss": -0.5229212641716003
    },
    {
      "epoch": 37,
      "value_loss": 0.1066456139087677,
      "q_loss": 380.468017578125,
      "actor_loss": -0.5451703667640686
    },
    {
      "epoch": 38,
      "value_loss": 0.10505764186382294,
      "q_loss": 380.9014892578125,
      "actor_loss": -0.5492905378341675
    },
    {
      "epoch": 39,
      "value_loss": 0.10402435809373856,
      "q_loss": 380.7348937988281,
      "actor_loss": -0.5662717223167419
    },
    {
      "epoch": 40,
      "value_loss": 0.09972620755434036,
      "q_loss": 380.8802185058594,
      "actor_loss": -0.5832183957099915
    },
    {
      "epoch": 41,
      "value_loss": 0.09906994551420212,
      "q_loss": 380.6982116699219,
      "actor_loss": -0.5988434553146362
    },
    {
      "epoch": 42,
      "value_loss": 0.10100462287664413,
      "q_loss": 381.4246520996094,
      "actor_loss": -0.6154982447624207
    },
    {
      "epoch": 43,
      "value_loss": 0.09548673033714294,
      "q_loss": 380.8768005371094,
      "actor_loss": -0.6222343444824219
    },
    {
      "epoch": 44,
      "value_loss": 0.09213389456272125,
      "q_loss": 381.38079833984375,
      "actor_loss": -0.6363126039505005
    },
    {
      "epoch": 45,
      "value_loss": 0.0974830687046051,
      "q_loss": 381.7192077636719,
      "actor_loss": -0.64979487657547
    },
    {
      "epoch": 46,
      "value_loss": 0.09748498350381851,
      "q_loss": 381.97344970703125,
      "actor_loss": -0.6634781360626221
    },
    {
      "epoch": 47,
      "value_loss": 0.08867411315441132,
      "q_loss": 381.7812194824219,
      "actor_loss": -0.6736211776733398
    },
    {
      "epoch": 48,
      "value_loss": 0.09129359573125839,
      "q_loss": 381.6590881347656,
      "actor_loss": -0.6897543668746948
    },
    {
      "epoch": 49,
      "value_loss": 0.09665678441524506,
      "q_loss": 382.1137390136719,
      "actor_loss": -0.7023271918296814
    },
    {
      "epoch": 50,
      "value_loss": 0.08872499316930771,
      "q_loss": 381.7745666503906,
      "actor_loss": -0.7171633839607239
    },
    {
      "epoch": 51,
      "value_loss": 0.08859092742204666,
      "q_loss": 382.04541015625,
      "actor_loss": -0.7171406745910645
    },
    {
      "epoch": 52,
      "value_loss": 0.09101825952529907,
      "q_loss": 381.5625915527344,
      "actor_loss": -0.7295877933502197
    },
    {
      "epoch": 53,
      "value_loss": 0.0956978127360344,
      "q_loss": 381.9342346191406,
      "actor_loss": -0.738865315914154
    },
    {
      "epoch": 54,
      "value_loss": 0.08072827011346817,
      "q_loss": 381.8618469238281,
      "actor_loss": -0.7468626499176025
    },
    {
      "epoch": 55,
      "value_loss": 0.08659454435110092,
      "q_loss": 382.1073303222656,
      "actor_loss": -0.7507272958755493
    },
    {
      "epoch": 56,
      "value_loss": 0.08486421406269073,
      "q_loss": 382.1571350097656,
      "actor_loss": -0.7590129971504211
    },
    {
      "epoch": 57,
      "value_loss": 0.09010562300682068,
      "q_loss": 382.2744445800781,
      "actor_loss": -0.7708819508552551
    },
    {
      "epoch": 58,
      "value_loss": 0.08495517075061798,
      "q_loss": 381.9248046875,
      "actor_loss": -0.7864546775817871
    },
    {
      "epoch": 59,
      "value_loss": 0.0802672952413559,
      "q_loss": 381.8666076660156,
      "actor_loss": -0.7931756377220154
    },
    {
      "epoch": 60,
      "value_loss": 0.0825730636715889,
      "q_loss": 382.1983337402344,
      "actor_loss": -0.7953557372093201
    },
    {
      "epoch": 61,
      "value_loss": 0.07960938662290573,
      "q_loss": 382.41363525390625,
      "actor_loss": -0.8112520575523376
    },
    {
      "epoch": 62,
      "value_loss": 0.0801176056265831,
      "q_loss": 382.1248474121094,
      "actor_loss": -0.8156254291534424
    },
    {
      "epoch": 63,
      "value_loss": 0.07782947272062302,
      "q_loss": 382.48028564453125,
      "actor_loss": -0.8253042697906494
    },
    {
      "epoch": 64,
      "value_loss": 0.08089258521795273,
      "q_loss": 381.7274475097656,
      "actor_loss": -0.828758180141449
    },
    {
      "epoch": 65,
      "value_loss": 0.07602532207965851,
      "q_loss": 382.23797607421875,
      "actor_loss": -0.840212345123291
    },
    {
      "epoch": 66,
      "value_loss": 0.07899849116802216,
      "q_loss": 381.93157958984375,
      "actor_loss": -0.8498285412788391
    },
    {
      "epoch": 67,
      "value_loss": 0.0839834213256836,
      "q_loss": 382.2301025390625,
      "actor_loss": -0.8529176115989685
    },
    {
      "epoch": 68,
      "value_loss": 0.07816285640001297,
      "q_loss": 381.94329833984375,
      "actor_loss": -0.8566768765449524
    },
    {
      "epoch": 69,
      "value_loss": 0.07588356733322144,
      "q_loss": 382.5282287597656,
      "actor_loss": -0.8724746108055115
    },
    {
      "epoch": 70,
      "value_loss": 0.07527898997068405,
      "q_loss": 382.04052734375,
      "actor_loss": -0.8785454034805298
    },
    {
      "epoch": 71,
      "value_loss": 0.07844095677137375,
      "q_loss": 381.91729736328125,
      "actor_loss": -0.8807820081710815
    },
    {
      "epoch": 72,
      "value_loss": 0.07455853372812271,
      "q_loss": 382.10150146484375,
      "actor_loss": -0.8858655691146851
    },
    {
      "epoch": 73,
      "value_loss": 0.07437793910503387,
      "q_loss": 381.78424072265625,
      "actor_loss": -0.8973996639251709
    },
    {
      "epoch": 74,
      "value_loss": 0.07433751970529556,
      "q_loss": 381.5133056640625,
      "actor_loss": -0.8967332243919373
    },
    {
      "epoch": 75,
      "value_loss": 0.0723467618227005,
      "q_loss": 381.4660339355469,
      "actor_loss": -0.9069176316261292
    },
    {
      "epoch": 76,
      "value_loss": 0.07028528302907944,
      "q_loss": 381.7320556640625,
      "actor_loss": -0.9117180705070496
    },
    {
      "epoch": 77,
      "value_loss": 0.07077904790639877,
      "q_loss": 381.7508850097656,
      "actor_loss": -0.9177200794219971
    },
    {
      "epoch": 78,
      "value_loss": 0.06845143437385559,
      "q_loss": 381.6321105957031,
      "actor_loss": -0.9257524013519287
    },
    {
      "epoch": 79,
      "value_loss": 0.06902124732732773,
      "q_loss": 381.8992614746094,
      "actor_loss": -0.9310006499290466
    },
    {
      "epoch": 80,
      "value_loss": 0.07128123193979263,
      "q_loss": 381.8966369628906,
      "actor_loss": -0.9397174119949341
    },
    {
      "epoch": 81,
      "value_loss": 0.07075811177492142,
      "q_loss": 381.46441650390625,
      "actor_loss": -0.9497294425964355
    },
    {
      "epoch": 82,
      "value_loss": 0.06805398315191269,
      "q_loss": 381.8938293457031,
      "actor_loss": -0.9468005895614624
    },
    {
      "epoch": 83,
      "value_loss": 0.06753295660018921,
      "q_loss": 381.51458740234375,
      "actor_loss": -0.9545487761497498
    },
    {
      "epoch": 84,
      "value_loss": 0.07122627645730972,
      "q_loss": 382.2767639160156,
      "actor_loss": -0.9589970707893372
    },
    {
      "epoch": 85,
      "value_loss": 0.06256410479545593,
      "q_loss": 381.9669494628906,
      "actor_loss": -0.9708445072174072
    },
    {
      "epoch": 86,
      "value_loss": 0.06917127966880798,
      "q_loss": 381.2901916503906,
      "actor_loss": -0.9653154015541077
    },
    {
      "epoch": 87,
      "value_loss": 0.0666765347123146,
      "q_loss": 381.1518249511719,
      "actor_loss": -0.9752501249313354
    },
    {
      "epoch": 88,
      "value_loss": 0.06487595289945602,
      "q_loss": 381.4608459472656,
      "actor_loss": -0.9818123579025269
    },
    {
      "epoch": 89,
      "value_loss": 0.06769834458827972,
      "q_loss": 381.6135559082031,
      "actor_loss": -0.9879264235496521
    },
    {
      "epoch": 90,
      "value_loss": 0.06543584913015366,
      "q_loss": 381.16741943359375,
      "actor_loss": -0.9899292588233948
    },
    {
      "epoch": 91,
      "value_loss": 0.06791646033525467,
      "q_loss": 381.3901062011719,
      "actor_loss": -0.9872987866401672
    },
    {
      "epoch": 92,
      "value_loss": 0.06094672158360481,
      "q_loss": 380.99090576171875,
      "actor_loss": -0.9944050312042236
    },
    {
      "epoch": 93,
      "value_loss": 0.06273164600133896,
      "q_loss": 381.47882080078125,
      "actor_loss": -1.004825472831726
    },
    {
      "epoch": 94,
      "value_loss": 0.06509637087583542,
      "q_loss": 381.412353515625,
      "actor_loss": -0.9989032745361328
    },
    {
      "epoch": 95,
      "value_loss": 0.060138072818517685,
      "q_loss": 381.62054443359375,
      "actor_loss": -1.0143157243728638
    },
    {
      "epoch": 96,
      "value_loss": 0.06324059516191483,
      "q_loss": 381.4903564453125,
      "actor_loss": -1.0140634775161743
    },
    {
      "epoch": 97,
      "value_loss": 0.0594695545732975,
      "q_loss": 381.3851623535156,
      "actor_loss": -1.0171464681625366
    },
    {
      "epoch": 98,
      "value_loss": 0.061093736439943314,
      "q_loss": 380.976806640625,
      "actor_loss": -1.0221799612045288
    },
    {
      "epoch": 99,
      "value_loss": 0.06021494418382645,
      "q_loss": 381.0732727050781,
      "actor_loss": -1.0159943103790283
    },
    {
      "epoch": 100,
      "value_loss": 0.061192356050014496,
      "q_loss": 380.85791015625,
      "actor_loss": -1.032303810119629
    }
  ]
}