{
  "env": "halfcheetah-medium-v2",
  "method": "plain_td3bc",
  "seed": 2,
  "noise_dim": 4,
  "noise_scale": 1.5,
  "noise_type": "nonlinear",
  "avg_return": 4854.5937817812155,
  "std_return": 947.2070850906725,
  "normalized_score": 41.35882981807886,
  "latent_dim": 25,
  "pretrain_epochs": 50,
  "td3bc_epochs": 100,
  "encoder_checkpoint": "/home/compute/wyuhan/robust-offline-rl-disentanglement/artifacts/checkpoints/plain_td3bc/halfcheetah-medium-v2/nd4_ns1p5_nonlinear/seed_2/encoder_epoch_50.pth",
  "obs_stats_path": "/home/compute/wyuhan/robust-offline-rl-disentanglement/artifacts/obs_stats/plain_td3bc/halfcheetah-medium-v2/nd4_ns1p5_nonlinear/seed_2/obs_stats.npz",
  "td3bc_history": [
    {
      "epoch": 1,
      "q_loss": 10.80114249210219,
      "actor_loss": -2.4079112903740976
    },
    {
      "epoch": 2,
      "q_loss": 59.21259262277356,
      "actor_loss": -2.4403265752489607
    },
    {
      "epoch": 3,
      "q_loss": 123.87631457192558,
      "actor_loss": -2.4445804542477045
    },
    {
      "epoch": 4,
      "q_loss": 191.73781601221697,
      "actor_loss": -2.446581935125684
    },
    {
      "epoch": 5,
      "q_loss": 253.79389399964566,
      "actor_loss": -2.446634908181487
    },
    {
      "epoch": 6,
      "q_loss": 311.7799578303871,
      "actor_loss": -2.4451316178791105
    },
    {
      "epoch": 7,
      "q_loss": 359.2132203326247,
      "actor_loss": -2.4440660217878944
    },
    {
      "epoch": 8,
      "q_loss": 401.8698032797146,
      "actor_loss": -2.4417533355679684
    },
    {
      "epoch": 9,
      "q_loss": 433.01278707911524,
      "actor_loss": -2.4401524325120283
    },
    {
      "epoch": 10,
      "q_loss": 459.1582435338362,
      "actor_loss": -2.438354296740421
    },
    {
      "epoch": 11,
      "q_loss": 476.1300168034973,
      "actor_loss": -2.437377011476879
    },
    {
      "epoch": 12,
      "q_loss": 488.3514975710399,
      "actor_loss": -2.4363816653040207
    },
    {
      "epoch": 13,
      "q_loss": 494.8096264869936,
      "actor_loss": -2.4364956204731283
    },
    {
      "epoch": 14,
      "q_loss": 500.14492078567247,
      "actor_loss": -2.4362111711770646
    },
    {
      "epoch": 15,
      "q_loss": 501.226844528792,
      "actor_loss": -2.4362451965480476
    },
    {
      "epoch": 16,
      "q_loss": 500.76189147345667,
      "actor_loss": -2.436413223048814
    },
    {
      "epoch": 17,
      "q_loss": 500.2268392281598,
      "actor_loss": -2.437035842669419
    },
    {
      "epoch": 18,
      "q_loss": 496.42597222218313,
      "actor_loss": -2.4374184230627676
    },
    {
      "epoch": 19,
      "q_loss": 494.81883206785,
      "actor_loss": -2.437857494193105
    },
    {
      "epoch": 20,
      "q_loss": 491.8118421751844,
      "actor_loss": -2.43855201581534
    },
    {
      "epoch": 21,
      "q_loss": 489.2239096168366,
      "actor_loss": -2.439095856102076
    },
    {
      "epoch": 22,
      "q_loss": 486.4168582052923,
      "actor_loss": -2.4392139650404423
    },
    {
      "epoch": 23,
      "q_loss": 483.61845788110907,
      "actor_loss": -2.439520492653815
    },
    {
      "epoch": 24,
      "q_loss": 481.6164369197363,
      "actor_loss": -2.4396380158613353
    },
    {
      "epoch": 25,
      "q_loss": 478.3346652896723,
      "actor_loss": -2.440075160904048
    },
    {
      "epoch": 26,
      "q_loss": 476.6598886508424,
      "actor_loss": -2.440095767325398
    },
    {
      "epoch": 27,
      "q_loss": 474.3764933572936,
      "actor_loss": -2.4401191930800175
    },
    {
      "epoch": 28,
      "q_loss": 472.4785488224371,
      "actor_loss": -2.440265528922562
    },
    {
      "epoch": 29,
      "q_loss": 470.0073995546262,
      "actor_loss": -2.440502265387172
    },
    {
      "epoch": 30,
      "q_loss": 469.1699901410878,
      "actor_loss": -2.440662403382586
    },
    {
      "epoch": 31,
      "q_loss": 465.8526730339648,
      "actor_loss": -2.440920188313439
    },
    {
      "epoch": 32,
      "q_loss": 463.9928811527922,
      "actor_loss": -2.4413188704453064
    },
    {
      "epoch": 33,
      "q_loss": 462.9554871213906,
      "actor_loss": -2.44157781975732
    },
    {
      "epoch": 34,
      "q_loss": 461.77908665842114,
      "actor_loss": -2.4417414233065604
    },
    {
      "epoch": 35,
      "q_loss": 460.49060663466446,
      "actor_loss": -2.4417629558125706
    },
    {
      "epoch": 36,
      "q_loss": 460.0229343315668,
      "actor_loss": -2.441713484872993
    },
    {
      "epoch": 37,
      "q_loss": 458.48168393421713,
      "actor_loss": -2.4420549680316257
    },
    {
      "epoch": 38,
      "q_loss": 457.30860523169184,
      "actor_loss": -2.442030866574582
    },
    {
      "epoch": 39,
      "q_loss": 457.2254752722143,
      "actor_loss": -2.442391942661967
    },
    {
      "epoch": 40,
      "q_loss": 455.389635700845,
      "actor_loss": -2.442636519716266
    },
    {
      "epoch": 41,
      "q_loss": 455.045303287594,
      "actor_loss": -2.4429967715931866
    },
    {
      "epoch": 42,
      "q_loss": 454.056779365813,
      "actor_loss": -2.4434079166808864
    },
    {
      "epoch": 43,
      "q_loss": 453.0990043436022,
      "actor_loss": -2.4436811137919663
    },
    {
      "epoch": 44,
      "q_loss": 452.6599820552578,
      "actor_loss": -2.443863348538486
    },
    {
      "epoch": 45,
      "q_loss": 452.16193915805144,
      "actor_loss": -2.444249643402959
    },
    {
      "epoch": 46,
      "q_loss": 451.33603058261747,
      "actor_loss": -2.444300836437614
    },
    {
      "epoch": 47,
      "q_loss": 450.8391795043633,
      "actor_loss": -2.4448353423867175
    },
    {
      "epoch": 48,
      "q_loss": 449.738164574564,
      "actor_loss": -2.4453029239476796
    },
    {
      "epoch": 49,
      "q_loss": 449.1712049087743,
      "actor_loss": -2.4457816010673903
    },
    {
      "epoch": 50,
      "q_loss": 448.81711863543643,
      "actor_loss": -2.4459262819578265
    },
    {
      "epoch": 51,
      "q_loss": 448.62172158510333,
      "actor_loss": -2.4464400362126106
    },
    {
      "epoch": 52,
      "q_loss": 448.6270485803279,
      "actor_loss": -2.446722469693627
    },
    {
      "epoch": 53,
      "q_loss": 447.5849763667101,
      "actor_loss": -2.4468191604521476
    },
    {
      "epoch": 54,
      "q_loss": 447.35864874795345,
      "actor_loss": -2.4473254081229947
    },
    {
      "epoch": 55,
      "q_loss": 447.2225975362814,
      "actor_loss": -2.4475083779019084
    },
    {
      "epoch": 56,
      "q_loss": 446.54655723503413,
      "actor_loss": -2.4479091814464016
    },
    {
      "epoch": 57,
      "q_loss": 446.5623387113572,
      "actor_loss": -2.4482051508278952
    },
    {
      "epoch": 58,
      "q_loss": 446.08484854261144,
      "actor_loss": -2.448517348848119
    },
    {
      "epoch": 59,
      "q_loss": 445.2747190229354,
      "actor_loss": -2.4488098424212237
    },
    {
      "epoch": 60,
      "q_loss": 445.20151034050946,
      "actor_loss": -2.4492470834783817
    },
    {
      "epoch": 61,
      "q_loss": 444.80455906453403,
      "actor_loss": -2.4493425269646947
    },
    {
      "epoch": 62,
      "q_loss": 444.7541696535766,
      "actor_loss": -2.4496980007648226
    },
    {
      "epoch": 63,
      "q_loss": 444.44619086334416,
      "actor_loss": -2.450161217971759
    },
    {
      "epoch": 64,
      "q_loss": 444.5861398215423,
      "actor_loss": -2.450403854228018
    },
    {
      "epoch": 65,
      "q_loss": 443.9370240471757,
      "actor_loss": -2.450663163304268
    },
    {
      "epoch": 66,
      "q_loss": 443.89091955254275,
      "actor_loss": -2.451068905214133
    },
    {
      "epoch": 67,
      "q_loss": 443.8476254535954,
      "actor_loss": -2.451467319750749
    },
    {
      "epoch": 68,
      "q_loss": 443.48025666220764,
      "actor_loss": -2.451597823464315
    },
    {
      "epoch": 69,
      "q_loss": 442.71174775498133,
      "actor_loss": -2.451665116162161
    },
    {
      "epoch": 70,
      "q_loss": 442.86882647842975,
      "actor_loss": -2.451818094214475
    },
    {
      "epoch": 71,
      "q_loss": 443.3908874332996,
      "actor_loss": -2.4519634395151093
    },
    {
      "epoch": 72,
      "q_loss": 442.62576918497,
      "actor_loss": -2.452176744914702
    },
    {
      "epoch": 73,
      "q_loss": 442.93833051653195,
      "actor_loss": -2.4523239279183984
    },
    {
      "epoch": 74,
      "q_loss": 443.54715215348,
      "actor_loss": -2.4525497559700264
    },
    {
      "epoch": 75,
      "q_loss": 442.2470855454085,
      "actor_loss": -2.4526189334320523
    },
    {
      "epoch": 76,
      "q_loss": 443.21934181277834,
      "actor_loss": -2.4525922433083567
    },
    {
      "epoch": 77,
      "q_loss": 442.6752071942175,
      "actor_loss": -2.452773909903281
    },
    {
      "epoch": 78,
      "q_loss": 442.54145077296664,
      "actor_loss": -2.453013485844051
    },
    {
      "epoch": 79,
      "q_loss": 442.8011367585924,
      "actor_loss": -2.453169459876682
    },
    {
      "epoch": 80,
      "q_loss": 441.83552493990476,
      "actor_loss": -2.453422842487212
    },
    {
      "epoch": 81,
      "q_loss": 441.0932318828561,
      "actor_loss": -2.453659904473144
    },
    {
      "epoch": 82,
      "q_loss": 441.7639173501831,
      "actor_loss": -2.453910721733945
    },
    {
      "epoch": 83,
      "q_loss": 440.9831478443136,
      "actor_loss": -2.4540604373704333
    },
    {
      "epoch": 84,
      "q_loss": 441.3600428664739,
      "actor_loss": -2.4543297838322395
    },
    {
      "epoch": 85,
      "q_loss": 441.3162094629916,
      "actor_loss": -2.4544631330037934
    },
    {
      "epoch": 86,
      "q_loss": 440.6214779694143,
      "actor_loss": -2.454678950832248
    },
    {
      "epoch": 87,
      "q_loss": 440.07750231219876,
      "actor_loss": -2.4550975439063842
    },
    {
      "epoch": 88,
      "q_loss": 439.7977129852717,
      "actor_loss": -2.4552140401316738
    },
    {
      "epoch": 89,
      "q_loss": 439.1518247568235,
      "actor_loss": -2.455313529531222
    },
    {
      "epoch": 90,
      "q_loss": 439.6750490551903,
      "actor_loss": -2.455298351740996
    },
    {
      "epoch": 91,
      "q_loss": 440.5078676348763,
      "actor_loss": -2.4551470622122746
    },
    {
      "epoch": 92,
      "q_loss": 441.0905274807705,
      "actor_loss": -2.4549853909156045
    },
    {
      "epoch": 93,
      "q_loss": 439.4581209305794,
      "actor_loss": -2.4550397515113818
    },
    {
      "epoch": 94,
      "q_loss": 439.2340401289589,
      "actor_loss": -2.4549697022894623
    },
    {
      "epoch": 95,
      "q_loss": 440.09150452376997,
      "actor_loss": -2.4548500001705187
    },
    {
      "epoch": 96,
      "q_loss": 438.94268068459115,
      "actor_loss": -2.45489249458938
    },
    {
      "epoch": 97,
      "q_loss": 439.2443665461972,
      "actor_loss": -2.4548045298531918
    },
    {
      "epoch": 98,
      "q_loss": 439.4868144178415,
      "actor_loss": -2.4548274180367855
    },
    {
      "epoch": 99,
      "q_loss": 439.0600066338816,
      "actor_loss": -2.454792777514128
    },
    {
      "epoch": 100,
      "q_loss": 438.1118150067464,
      "actor_loss": -2.4546956560029414
    }
  ]
}