{
  "env": "hopper-medium-v2",
  "method": "disentangled_dcor",
  "seed": 2,
  "noise_dim": 8,
  "noise_scale": 2.0,
  "noise_type": "nonlinear",
  "avg_return": 1271.7441423741843,
  "std_return": 292.68092593505526,
  "normalized_score": 39.69850187040734,
  "latent_dim": 16,
  "pretrain_epochs": 50,
  "iql_epochs": 100,
  "encoder_checkpoint": "/home/compute/wyuhan/robust-offline-rl-disentanglement/artifacts/checkpoints/disentangled_dcor/hopper-medium-v2/nd8_ns2p0_nonlinear/seed_2/encoder_epoch_50.pth",
  "obs_stats_path": "/home/compute/wyuhan/robust-offline-rl-disentanglement/artifacts/obs_stats/disentangled_dcor/hopper-medium-v2/nd8_ns2p0_nonlinear/seed_2/obs_stats.npz",
  "iql_history": [
    {
      "epoch": 1,
      "value_loss": 0.019343679770827293,
      "q_loss": 6.246597766876221,
      "actor_loss": 0.9713743925094604
    },
    {
      "epoch": 2,
      "value_loss": 0.07063601911067963,
      "q_loss": 27.420204162597656,
      "actor_loss": 0.32118284702301025
    },
    {
      "epoch": 3,
      "value_loss": 0.09569010883569717,
      "q_loss": 56.975006103515625,
      "actor_loss": 0.11043205112218857
    },
    {
      "epoch": 4,
      "value_loss": 0.09494317322969437,
      "q_loss": 88.07003021240234,
      "actor_loss": -0.01154527347534895
    },
    {
      "epoch": 5,
      "value_loss": 0.09261372685432434,
      "q_loss": 119.08513641357422,
      "actor_loss": -0.09435204416513443
    },
    {
      "epoch": 6,
      "value_loss": 0.08883845806121826,
      "q_loss": 146.353271484375,
      "actor_loss": -0.15232577919960022
    },
    {
      "epoch": 7,
      "value_loss": 0.08247707784175873,
      "q_loss": 170.2093048095703,
      "actor_loss": -0.19794858992099762
    },
    {
      "epoch": 8,
      "value_loss": 0.07779816538095474,
      "q_loss": 190.38194274902344,
      "actor_loss": -0.23195424675941467
    },
    {
      "epoch": 9,
      "value_loss": 0.07847421616315842,
      "q_loss": 206.8694610595703,
      "actor_loss": -0.26027753949165344
    },
    {
      "epoch": 10,
      "value_loss": 0.07332808524370193,
      "q_loss": 220.2489471435547,
      "actor_loss": -0.2877050042152405
    },
    {
      "epoch": 11,
      "value_loss": 0.0710429698228836,
      "q_loss": 231.3828582763672,
      "actor_loss": -0.3057510256767273
    },
    {
      "epoch": 12,
      "value_loss": 0.06846554577350616,
      "q_loss": 240.3948974609375,
      "actor_loss": -0.330798864364624
    },
    {
      "epoch": 13,
      "value_loss": 0.0690637156367302,
      "q_loss": 247.16612243652344,
      "actor_loss": -0.34848466515541077
    },
    {
      "epoch": 14,
      "value_loss": 0.06692808121442795,
      "q_loss": 253.13304138183594,
      "actor_loss": -0.362452894449234
    },
    {
      "epoch": 15,
      "value_loss": 0.06636738032102585,
      "q_loss": 257.5091247558594,
      "actor_loss": -0.3748388886451721
    },
    {
      "epoch": 16,
      "value_loss": 0.06619872152805328,
      "q_loss": 261.2575378417969,
      "actor_loss": -0.3879077732563019
    },
    {
      "epoch": 17,
      "value_loss": 0.06726714223623276,
      "q_loss": 263.89971923828125,
      "actor_loss": -0.39870426058769226
    },
    {
      "epoch": 18,
      "value_loss": 0.06303782016038895,
      "q_loss": 266.1454162597656,
      "actor_loss": -0.4095001816749573
    },
    {
      "epoch": 19,
      "value_loss": 0.06076482683420181,
      "q_loss": 267.61761474609375,
      "actor_loss": -0.4173646867275238
    },
    {
      "epoch": 20,
      "value_loss": 0.059755414724349976,
      "q_loss": 269.3624572753906,
      "actor_loss": -0.42284849286079407
    },
    {
      "epoch": 21,
      "value_loss": 0.06661101430654526,
      "q_loss": 270.6285705566406,
      "actor_loss": -0.43325600028038025
    },
    {
      "epoch": 22,
      "value_loss": 0.0597822330892086,
      "q_loss": 271.1881103515625,
      "actor_loss": -0.43973013758659363
    },
    {
      "epoch": 23,
      "value_loss": 0.0579829216003418,
      "q_loss": 271.77264404296875,
      "actor_loss": -0.4475110173225403
    },
    {
      "epoch": 24,
      "value_loss": 0.05579884350299835,
      "q_loss": 272.890625,
      "actor_loss": -0.45125147700309753
    },
    {
      "epoch": 25,
      "value_loss": 0.05302375927567482,
      "q_loss": 273.02764892578125,
      "actor_loss": -0.45724692940711975
    },
    {
      "epoch": 26,
      "value_loss": 0.05658794194459915,
      "q_loss": 273.78851318359375,
      "actor_loss": -0.46312615275382996
    },
    {
      "epoch": 27,
      "value_loss": 0.05106170475482941,
      "q_loss": 273.7140197753906,
      "actor_loss": -0.46934160590171814
    },
    {
      "epoch": 28,
      "value_loss": 0.05020041763782501,
      "q_loss": 274.2096862792969,
      "actor_loss": -0.47635501623153687
    },
    {
      "epoch": 29,
      "value_loss": 0.050813447684049606,
      "q_loss": 274.3349304199219,
      "actor_loss": -0.47902926802635193
    },
    {
      "epoch": 30,
      "value_loss": 0.0582658052444458,
      "q_loss": 274.8888854980469,
      "actor_loss": -0.484305739402771
    },
    {
      "epoch": 31,
      "value_loss": 0.04836064949631691,
      "q_loss": 274.7615661621094,
      "actor_loss": -0.4881722629070282
    },
    {
      "epoch": 32,
      "value_loss": 0.050995320081710815,
      "q_loss": 274.6758728027344,
      "actor_loss": -0.495349258184433
    },
    {
      "epoch": 33,
      "value_loss": 0.04930451139807701,
      "q_loss": 274.81610107421875,
      "actor_loss": -0.49644342064857483
    },
    {
      "epoch": 34,
      "value_loss": 0.05108705163002014,
      "q_loss": 274.71722412109375,
      "actor_loss": -0.5031447410583496
    },
    {
      "epoch": 35,
      "value_loss": 0.05207618325948715,
      "q_loss": 274.7958984375,
      "actor_loss": -0.5029961466789246
    },
    {
      "epoch": 36,
      "value_loss": 0.05103608965873718,
      "q_loss": 274.4465026855469,
      "actor_loss": -0.5080355405807495
    },
    {
      "epoch": 37,
      "value_loss": 0.05429702624678612,
      "q_loss": 274.5558166503906,
      "actor_loss": -0.5114101767539978
    },
    {
      "epoch": 38,
      "value_loss": 0.05245162174105644,
      "q_loss": 274.1894226074219,
      "actor_loss": -0.5142285823822021
    },
    {
      "epoch": 39,
      "value_loss": 0.06064610183238983,
      "q_loss": 274.0375061035156,
      "actor_loss": -0.5181662440299988
    },
    {
      "epoch": 40,
      "value_loss": 0.06753571331501007,
      "q_loss": 273.70501708984375,
      "actor_loss": -0.5236517190933228
    },
    {
      "epoch": 41,
      "value_loss": 0.05367420241236687,
      "q_loss": 273.18743896484375,
      "actor_loss": -0.5265979766845703
    },
    {
      "epoch": 42,
      "value_loss": 0.057790178805589676,
      "q_loss": 272.8916931152344,
      "actor_loss": -0.5277870297431946
    },
    {
      "epoch": 43,
      "value_loss": 0.05926330015063286,
      "q_loss": 273.0494384765625,
      "actor_loss": -0.529446005821228
    },
    {
      "epoch": 44,
      "value_loss": 0.05918102711439133,
      "q_loss": 272.7929992675781,
      "actor_loss": -0.5340550541877747
    },
    {
      "epoch": 45,
      "value_loss": 0.061228130012750626,
      "q_loss": 272.4530334472656,
      "actor_loss": -0.538249671459198
    },
    {
      "epoch": 46,
      "value_loss": 0.06214958056807518,
      "q_loss": 271.9593811035156,
      "actor_loss": -0.5390614867210388
    },
    {
      "epoch": 47,
      "value_loss": 0.06222939118742943,
      "q_loss": 271.8050537109375,
      "actor_loss": -0.5417768359184265
    },
    {
      "epoch": 48,
      "value_loss": 0.061874162405729294,
      "q_loss": 271.28936767578125,
      "actor_loss": -0.5454836487770081
    },
    {
      "epoch": 49,
      "value_loss": 0.061371397227048874,
      "q_loss": 271.0756530761719,
      "actor_loss": -0.5466443300247192
    },
    {
      "epoch": 50,
      "value_loss": 0.060493435710668564,
      "q_loss": 270.81439208984375,
      "actor_loss": -0.5470345616340637
    },
    {
      "epoch": 51,
      "value_loss": 0.06057816371321678,
      "q_loss": 270.83941650390625,
      "actor_loss": -0.5500645041465759
    },
    {
      "epoch": 52,
      "value_loss": 0.059370432049036026,
      "q_loss": 270.6585388183594,
      "actor_loss": -0.554071843624115
    },
    {
      "epoch": 53,
      "value_loss": 0.06814104318618774,
      "q_loss": 271.0797119140625,
      "actor_loss": -0.5543274879455566
    },
    {
      "epoch": 54,
      "value_loss": 0.05599457398056984,
      "q_loss": 270.51947021484375,
      "actor_loss": -0.5557087659835815
    },
    {
      "epoch": 55,
      "value_loss": 0.05771902948617935,
      "q_loss": 270.33416748046875,
      "actor_loss": -0.5574279427528381
    },
    {
      "epoch": 56,
      "value_loss": 0.055415499955415726,
      "q_loss": 270.3688659667969,
      "actor_loss": -0.5592043995857239
    },
    {
      "epoch": 57,
      "value_loss": 0.05580413341522217,
      "q_loss": 270.2007751464844,
      "actor_loss": -0.5622889399528503
    },
    {
      "epoch": 58,
      "value_loss": 0.05472170561552048,
      "q_loss": 270.17010498046875,
      "actor_loss": -0.5620185732841492
    },
    {
      "epoch": 59,
      "value_loss": 0.05515889823436737,
      "q_loss": 270.37646484375,
      "actor_loss": -0.5657368302345276
    },
    {
      "epoch": 60,
      "value_loss": 0.05397164449095726,
      "q_loss": 269.8421936035156,
      "actor_loss": -0.5671661496162415
    },
    {
      "epoch": 61,
      "value_loss": 0.05416572839021683,
      "q_loss": 270.1958923339844,
      "actor_loss": -0.5689180493354797
    },
    {
      "epoch": 62,
      "value_loss": 0.05429229512810707,
      "q_loss": 270.0126037597656,
      "actor_loss": -0.5690096020698547
    },
    {
      "epoch": 63,
      "value_loss": 0.05279024690389633,
      "q_loss": 269.9192199707031,
      "actor_loss": -0.5722215175628662
    },
    {
      "epoch": 64,
      "value_loss": 0.053244318813085556,
      "q_loss": 269.9872131347656,
      "actor_loss": -0.5726819038391113
    },
    {
      "epoch": 65,
      "value_loss": 0.052587106823921204,
      "q_loss": 269.8479309082031,
      "actor_loss": -0.5763178467750549
    },
    {
      "epoch": 66,
      "value_loss": 0.05456918105483055,
      "q_loss": 269.4427185058594,
      "actor_loss": -0.5774678587913513
    },
    {
      "epoch": 67,
      "value_loss": 0.05693208426237106,
      "q_loss": 269.7607727050781,
      "actor_loss": -0.5783459544181824
    },
    {
      "epoch": 68,
      "value_loss": 0.05289444699883461,
      "q_loss": 269.5057067871094,
      "actor_loss": -0.581223726272583
    },
    {
      "epoch": 69,
      "value_loss": 0.053563401103019714,
      "q_loss": 269.7724914550781,
      "actor_loss": -0.5822020769119263
    },
    {
      "epoch": 70,
      "value_loss": 0.05373965576291084,
      "q_loss": 269.8621520996094,
      "actor_loss": -0.5848172903060913
    },
    {
      "epoch": 71,
      "value_loss": 0.05200667306780815,
      "q_loss": 269.5145263671875,
      "actor_loss": -0.5835148692131042
    },
    {
      "epoch": 72,
      "value_loss": 0.05291876941919327,
      "q_loss": 269.48223876953125,
      "actor_loss": -0.587146520614624
    },
    {
      "epoch": 73,
      "value_loss": 0.05188215523958206,
      "q_loss": 269.21051025390625,
      "actor_loss": -0.5872650146484375
    },
    {
      "epoch": 74,
      "value_loss": 0.05202006176114082,
      "q_loss": 269.1952819824219,
      "actor_loss": -0.5919024348258972
    },
    {
      "epoch": 75,
      "value_loss": 0.05747762694954872,
      "q_loss": 269.4310607910156,
      "actor_loss": -0.589415431022644
    },
    {
      "epoch": 76,
      "value_loss": 0.052184175699949265,
      "q_loss": 269.2527160644531,
      "actor_loss": -0.593705952167511
    },
    {
      "epoch": 77,
      "value_loss": 0.053647227585315704,
      "q_loss": 269.1712341308594,
      "actor_loss": -0.5925135612487793
    },
    {
      "epoch": 78,
      "value_loss": 0.0569990798830986,
      "q_loss": 269.2418212890625,
      "actor_loss": -0.5958110094070435
    },
    {
      "epoch": 79,
      "value_loss": 0.061043206602334976,
      "q_loss": 268.78887939453125,
      "actor_loss": -0.5963361859321594
    },
    {
      "epoch": 80,
      "value_loss": 0.05980363115668297,
      "q_loss": 268.6833190917969,
      "actor_loss": -0.5966653823852539
    },
    {
      "epoch": 81,
      "value_loss": 0.05864064395427704,
      "q_loss": 268.9624328613281,
      "actor_loss": -0.5994740724563599
    },
    {
      "epoch": 82,
      "value_loss": 0.052555184811353683,
      "q_loss": 268.5155334472656,
      "actor_loss": -0.6000762581825256
    },
    {
      "epoch": 83,
      "value_loss": 0.05694970488548279,
      "q_loss": 268.3468933105469,
      "actor_loss": -0.5998690128326416
    },
    {
      "epoch": 84,
      "value_loss": 0.05379819869995117,
      "q_loss": 268.4873352050781,
      "actor_loss": -0.6030564904212952
    },
    {
      "epoch": 85,
      "value_loss": 0.05255231633782387,
      "q_loss": 268.5024108886719,
      "actor_loss": -0.6041828989982605
    },
    {
      "epoch": 86,
      "value_loss": 0.05173170939087868,
      "q_loss": 268.3292541503906,
      "actor_loss": -0.6032603979110718
    },
    {
      "epoch": 87,
      "value_loss": 0.05168519169092178,
      "q_loss": 268.4504089355469,
      "actor_loss": -0.6055833697319031
    },
    {
      "epoch": 88,
      "value_loss": 0.052816059440374374,
      "q_loss": 268.4544677734375,
      "actor_loss": -0.6040273308753967
    },
    {
      "epoch": 89,
      "value_loss": 0.057306498289108276,
      "q_loss": 268.6759033203125,
      "actor_loss": -0.6077738404273987
    },
    {
      "epoch": 90,
      "value_loss": 0.049762796610593796,
      "q_loss": 268.42340087890625,
      "actor_loss": -0.6086922883987427
    },
    {
      "epoch": 91,
      "value_loss": 0.058011651039123535,
      "q_loss": 268.710693359375,
      "actor_loss": -0.6093058586120605
    },
    {
      "epoch": 92,
      "value_loss": 0.056182969361543655,
      "q_loss": 268.5721740722656,
      "actor_loss": -0.6087446808815002
    },
    {
      "epoch": 93,
      "value_loss": 0.05491611734032631,
      "q_loss": 268.7689514160156,
      "actor_loss": -0.6112502813339233
    },
    {
      "epoch": 94,
      "value_loss": 0.05108830705285072,
      "q_loss": 268.6263427734375,
      "actor_loss": -0.6150296330451965
    },
    {
      "epoch": 95,
      "value_loss": 0.04985994100570679,
      "q_loss": 268.4988098144531,
      "actor_loss": -0.6125141382217407
    },
    {
      "epoch": 96,
      "value_loss": 0.053862977772951126,
      "q_loss": 268.63287353515625,
      "actor_loss": -0.6162407398223877
    },
    {
      "epoch": 97,
      "value_loss": 0.05513891950249672,
      "q_loss": 268.9169616699219,
      "actor_loss": -0.6162183284759521
    },
    {
      "epoch": 98,
      "value_loss": 0.054652128368616104,
      "q_loss": 268.41656494140625,
      "actor_loss": -0.6181065440177917
    },
    {
      "epoch": 99,
      "value_loss": 0.0534600168466568,
      "q_loss": 268.6006774902344,
      "actor_loss": -0.6152793169021606
    },
    {
      "epoch": 100,
      "value_loss": 0.054393332451581955,
      "q_loss": 268.2871398925781,
      "actor_loss": -0.617327868938446
    }
  ]
}