{
  "env": "halfcheetah-medium-v2",
  "method": "disentangled_barlow_no_priv",
  "seed": 3,
  "noise_dim": 8,
  "noise_scale": 1.0,
  "noise_type": "nonlinear",
  "avg_return": 4289.151539393558,
  "std_return": 402.1540221523059,
  "normalized_score": 36.80438686942507,
  "latent_dim": 25,
  "pretrain_epochs": 50,
  "iql_epochs": 100,
  "encoder_checkpoint": "/workspace/robust-offline-rl-disentanglement/artifacts/checkpoints/disentangled_barlow_no_priv/halfcheetah-medium-v2/nd8_ns1p0_nonlinear/seed_3/encoder_epoch_50.pth",
  "obs_stats_path": "/workspace/robust-offline-rl-disentanglement/artifacts/obs_stats/disentangled_barlow_no_priv/halfcheetah-medium-v2/nd8_ns1p0_nonlinear/seed_3/obs_stats.npz",
  "iql_history": [
    {
      "epoch": 1,
      "value_loss": 0.07821673899888992,
      "q_loss": 9.718427658081055,
      "actor_loss": -1.9685852527618408
    },
    {
      "epoch": 2,
      "value_loss": 0.27783384919166565,
      "q_loss": 37.4842643737793,
      "actor_loss": -3.2064051628112793
    },
    {
      "epoch": 3,
      "value_loss": 0.3978137671947479,
      "q_loss": 74.65221405029297,
      "actor_loss": -3.5067219734191895
    },
    {
      "epoch": 4,
      "value_loss": 0.441896915435791,
      "q_loss": 114.27243041992188,
      "actor_loss": -3.639631509780884
    },
    {
      "epoch": 5,
      "value_loss": 0.43368256092071533,
      "q_loss": 150.03494262695312,
      "actor_loss": -3.7106103897094727
    },
    {
      "epoch": 6,
      "value_loss": 0.4129917323589325,
      "q_loss": 184.1028289794922,
      "actor_loss": -3.7573747634887695
    },
    {
      "epoch": 7,
      "value_loss": 0.381075918674469,
      "q_loss": 215.24427795410156,
      "actor_loss": -3.8024415969848633
    },
    {
      "epoch": 8,
      "value_loss": 0.35516977310180664,
      "q_loss": 240.99215698242188,
      "actor_loss": -3.7672154903411865
    },
    {
      "epoch": 9,
      "value_loss": 0.3268660306930542,
      "q_loss": 263.6924743652344,
      "actor_loss": -3.8502414226531982
    },
    {
      "epoch": 10,
      "value_loss": 0.3138350546360016,
      "q_loss": 282.5556945800781,
      "actor_loss": -3.865494966506958
    },
    {
      "epoch": 11,
      "value_loss": 0.2717646658420563,
      "q_loss": 297.97894287109375,
      "actor_loss": -3.8978219032287598
    },
    {
      "epoch": 12,
      "value_loss": 0.27847397327423096,
      "q_loss": 311.1490783691406,
      "actor_loss": -3.903946876525879
    },
    {
      "epoch": 13,
      "value_loss": 0.24284526705741882,
      "q_loss": 321.71533203125,
      "actor_loss": -3.9356460571289062
    },
    {
      "epoch": 14,
      "value_loss": 0.23309357464313507,
      "q_loss": 331.2189025878906,
      "actor_loss": -3.946165084838867
    },
    {
      "epoch": 15,
      "value_loss": 0.225995734333992,
      "q_loss": 338.666748046875,
      "actor_loss": -3.961272716522217
    },
    {
      "epoch": 16,
      "value_loss": 0.2035466730594635,
      "q_loss": 344.6890563964844,
      "actor_loss": -3.981708288192749
    },
    {
      "epoch": 17,
      "value_loss": 0.19041459262371063,
      "q_loss": 349.4356994628906,
      "actor_loss": -3.9898133277893066
    },
    {
      "epoch": 18,
      "value_loss": 0.18248270452022552,
      "q_loss": 353.976806640625,
      "actor_loss": -4.007697582244873
    },
    {
      "epoch": 19,
      "value_loss": 0.18394961953163147,
      "q_loss": 357.07220458984375,
      "actor_loss": -4.010431289672852
    },
    {
      "epoch": 20,
      "value_loss": 0.16867661476135254,
      "q_loss": 359.9612731933594,
      "actor_loss": -4.024600028991699
    },
    {
      "epoch": 21,
      "value_loss": 0.17312033474445343,
      "q_loss": 361.78277587890625,
      "actor_loss": -4.033664703369141
    },
    {
      "epoch": 22,
      "value_loss": 0.16582107543945312,
      "q_loss": 364.27471923828125,
      "actor_loss": -4.042394161224365
    },
    {
      "epoch": 23,
      "value_loss": 0.1620517522096634,
      "q_loss": 366.3745422363281,
      "actor_loss": -4.0464067459106445
    },
    {
      "epoch": 24,
      "value_loss": 0.16361449658870697,
      "q_loss": 367.4611511230469,
      "actor_loss": -4.047312259674072
    },
    {
      "epoch": 25,
      "value_loss": 0.1414290815591812,
      "q_loss": 368.2243347167969,
      "actor_loss": -4.065893650054932
    },
    {
      "epoch": 26,
      "value_loss": 0.15361618995666504,
      "q_loss": 369.45037841796875,
      "actor_loss": -4.0616679191589355
    },
    {
      "epoch": 27,
      "value_loss": 0.13758701086044312,
      "q_loss": 370.3008728027344,
      "actor_loss": -4.075862407684326
    },
    {
      "epoch": 28,
      "value_loss": 0.14268270134925842,
      "q_loss": 371.08319091796875,
      "actor_loss": -4.0805983543396
    },
    {
      "epoch": 29,
      "value_loss": 0.14057302474975586,
      "q_loss": 371.7537841796875,
      "actor_loss": -4.0853400230407715
    },
    {
      "epoch": 30,
      "value_loss": 0.13500727713108063,
      "q_loss": 372.4612121582031,
      "actor_loss": -4.087223052978516
    },
    {
      "epoch": 31,
      "value_loss": 0.13013435900211334,
      "q_loss": 372.6628112792969,
      "actor_loss": -4.098268032073975
    },
    {
      "epoch": 32,
      "value_loss": 0.1290569305419922,
      "q_loss": 373.1174621582031,
      "actor_loss": -4.099338054656982
    },
    {
      "epoch": 33,
      "value_loss": 0.13753806054592133,
      "q_loss": 373.9256896972656,
      "actor_loss": -4.100976943969727
    },
    {
      "epoch": 34,
      "value_loss": 0.12752677500247955,
      "q_loss": 374.210693359375,
      "actor_loss": -4.1087822914123535
    },
    {
      "epoch": 35,
      "value_loss": 0.1353965401649475,
      "q_loss": 374.362060546875,
      "actor_loss": -4.103153705596924
    },
    {
      "epoch": 36,
      "value_loss": 0.12660209834575653,
      "q_loss": 374.55499267578125,
      "actor_loss": -4.112129211425781
    },
    {
      "epoch": 37,
      "value_loss": 0.12151643633842468,
      "q_loss": 374.9725646972656,
      "actor_loss": -4.117876052856445
    },
    {
      "epoch": 38,
      "value_loss": 0.12169014662504196,
      "q_loss": 375.2274475097656,
      "actor_loss": -4.12171745300293
    },
    {
      "epoch": 39,
      "value_loss": 0.11679619550704956,
      "q_loss": 375.4969787597656,
      "actor_loss": -4.126364231109619
    },
    {
      "epoch": 40,
      "value_loss": 0.12380393594503403,
      "q_loss": 375.6467590332031,
      "actor_loss": -4.113382816314697
    },
    {
      "epoch": 41,
      "value_loss": 0.10552537441253662,
      "q_loss": 375.4203186035156,
      "actor_loss": -4.137850761413574
    },
    {
      "epoch": 42,
      "value_loss": 0.11766578257083893,
      "q_loss": 376.04888916015625,
      "actor_loss": -4.134592533111572
    },
    {
      "epoch": 43,
      "value_loss": 0.1103203147649765,
      "q_loss": 375.9290771484375,
      "actor_loss": -4.136305809020996
    },
    {
      "epoch": 44,
      "value_loss": 0.114593006670475,
      "q_loss": 376.54803466796875,
      "actor_loss": -4.143183708190918
    },
    {
      "epoch": 45,
      "value_loss": 0.10844900459051132,
      "q_loss": 376.6150207519531,
      "actor_loss": -4.142284870147705
    },
    {
      "epoch": 46,
      "value_loss": 0.10787519812583923,
      "q_loss": 376.614501953125,
      "actor_loss": -4.143929481506348
    },
    {
      "epoch": 47,
      "value_loss": 0.10791857540607452,
      "q_loss": 376.9007263183594,
      "actor_loss": -4.145629405975342
    },
    {
      "epoch": 48,
      "value_loss": 0.10208962857723236,
      "q_loss": 376.9203796386719,
      "actor_loss": -4.1548004150390625
    },
    {
      "epoch": 49,
      "value_loss": 0.10609307140111923,
      "q_loss": 376.9329833984375,
      "actor_loss": -4.146602153778076
    },
    {
      "epoch": 50,
      "value_loss": 0.10166946798563004,
      "q_loss": 377.1747131347656,
      "actor_loss": -4.15533971786499
    },
    {
      "epoch": 51,
      "value_loss": 0.10388151556253433,
      "q_loss": 377.33941650390625,
      "actor_loss": -4.158320903778076
    },
    {
      "epoch": 52,
      "value_loss": 0.10368920117616653,
      "q_loss": 377.1593017578125,
      "actor_loss": -4.161250591278076
    },
    {
      "epoch": 53,
      "value_loss": 0.10383031517267227,
      "q_loss": 377.3874816894531,
      "actor_loss": -4.16141414642334
    },
    {
      "epoch": 54,
      "value_loss": 0.1010400801897049,
      "q_loss": 377.7112731933594,
      "actor_loss": -4.161916255950928
    },
    {
      "epoch": 55,
      "value_loss": 0.10040383040904999,
      "q_loss": 377.22235107421875,
      "actor_loss": -4.168643951416016
    },
    {
      "epoch": 56,
      "value_loss": 0.10175970196723938,
      "q_loss": 377.8049011230469,
      "actor_loss": -4.1677021980285645
    },
    {
      "epoch": 57,
      "value_loss": 0.10272154211997986,
      "q_loss": 377.98828125,
      "actor_loss": -4.1724982261657715
    },
    {
      "epoch": 58,
      "value_loss": 0.09476453065872192,
      "q_loss": 378.0376281738281,
      "actor_loss": -4.176509380340576
    },
    {
      "epoch": 59,
      "value_loss": 0.10262473672628403,
      "q_loss": 378.0930480957031,
      "actor_loss": -4.176078796386719
    },
    {
      "epoch": 60,
      "value_loss": 0.10169641673564911,
      "q_loss": 378.3753662109375,
      "actor_loss": -4.177188873291016
    },
    {
      "epoch": 61,
      "value_loss": 0.09692303836345673,
      "q_loss": 378.3045959472656,
      "actor_loss": -4.183377742767334
    },
    {
      "epoch": 62,
      "value_loss": 0.09872181713581085,
      "q_loss": 378.2772521972656,
      "actor_loss": -4.182239532470703
    },
    {
      "epoch": 63,
      "value_loss": 0.09043264389038086,
      "q_loss": 378.3653869628906,
      "actor_loss": -4.185276031494141
    },
    {
      "epoch": 64,
      "value_loss": 0.0969022661447525,
      "q_loss": 378.4454650878906,
      "actor_loss": -4.189342021942139
    },
    {
      "epoch": 65,
      "value_loss": 0.09501459449529648,
      "q_loss": 378.4452819824219,
      "actor_loss": -4.190803050994873
    },
    {
      "epoch": 66,
      "value_loss": 0.09200531989336014,
      "q_loss": 378.14215087890625,
      "actor_loss": -4.191831111907959
    },
    {
      "epoch": 67,
      "value_loss": 0.09219040721654892,
      "q_loss": 378.1234130859375,
      "actor_loss": -4.187593460083008
    },
    {
      "epoch": 68,
      "value_loss": 0.09483986347913742,
      "q_loss": 378.339599609375,
      "actor_loss": -4.198454856872559
    },
    {
      "epoch": 69,
      "value_loss": 0.092003732919693,
      "q_loss": 378.61871337890625,
      "actor_loss": -4.199570655822754
    },
    {
      "epoch": 70,
      "value_loss": 0.09310628473758698,
      "q_loss": 378.610107421875,
      "actor_loss": -4.199098587036133
    },
    {
      "epoch": 71,
      "value_loss": 0.0895204022526741,
      "q_loss": 378.7174987792969,
      "actor_loss": -4.202700614929199
    },
    {
      "epoch": 72,
      "value_loss": 0.09064266830682755,
      "q_loss": 378.95574951171875,
      "actor_loss": -4.203064918518066
    },
    {
      "epoch": 73,
      "value_loss": 0.0930383950471878,
      "q_loss": 378.8993835449219,
      "actor_loss": -4.202386379241943
    },
    {
      "epoch": 74,
      "value_loss": 0.08938279747962952,
      "q_loss": 378.7137145996094,
      "actor_loss": -4.206026077270508
    },
    {
      "epoch": 75,
      "value_loss": 0.09368009120225906,
      "q_loss": 378.91973876953125,
      "actor_loss": -4.207778453826904
    },
    {
      "epoch": 76,
      "value_loss": 0.09191225469112396,
      "q_loss": 378.9093017578125,
      "actor_loss": -4.2104997634887695
    },
    {
      "epoch": 77,
      "value_loss": 0.09489264339208603,
      "q_loss": 379.2069396972656,
      "actor_loss": -4.211121559143066
    },
    {
      "epoch": 78,
      "value_loss": 0.09920833259820938,
      "q_loss": 379.376708984375,
      "actor_loss": -4.209893226623535
    },
    {
      "epoch": 79,
      "value_loss": 0.0838167667388916,
      "q_loss": 379.0389709472656,
      "actor_loss": -4.217147350311279
    },
    {
      "epoch": 80,
      "value_loss": 0.087120421230793,
      "q_loss": 379.2103271484375,
      "actor_loss": -4.210979461669922
    },
    {
      "epoch": 81,
      "value_loss": 0.08714380860328674,
      "q_loss": 379.2903747558594,
      "actor_loss": -4.215910911560059
    },
    {
      "epoch": 82,
      "value_loss": 0.09195642918348312,
      "q_loss": 379.38494873046875,
      "actor_loss": -4.214766979217529
    },
    {
      "epoch": 83,
      "value_loss": 0.08972496539354324,
      "q_loss": 378.8825988769531,
      "actor_loss": -4.221980094909668
    },
    {
      "epoch": 84,
      "value_loss": 0.093996562063694,
      "q_loss": 379.1704406738281,
      "actor_loss": -4.218676567077637
    },
    {
      "epoch": 85,
      "value_loss": 0.10025037825107574,
      "q_loss": 379.4430236816406,
      "actor_loss": -4.216916084289551
    },
    {
      "epoch": 86,
      "value_loss": 0.08764442056417465,
      "q_loss": 379.5154113769531,
      "actor_loss": -4.224677562713623
    },
    {
      "epoch": 87,
      "value_loss": 0.10396270453929901,
      "q_loss": 379.7190246582031,
      "actor_loss": -4.222894191741943
    },
    {
      "epoch": 88,
      "value_loss": 0.09008673578500748,
      "q_loss": 379.2225646972656,
      "actor_loss": -4.224947452545166
    },
    {
      "epoch": 89,
      "value_loss": 0.09720353037118912,
      "q_loss": 379.8005676269531,
      "actor_loss": -4.220666408538818
    },
    {
      "epoch": 90,
      "value_loss": 0.08640765398740768,
      "q_loss": 379.6663513183594,
      "actor_loss": -4.228221416473389
    },
    {
      "epoch": 91,
      "value_loss": 0.08609730750322342,
      "q_loss": 379.50982666015625,
      "actor_loss": -4.23114538192749
    },
    {
      "epoch": 92,
      "value_loss": 0.08701208978891373,
      "q_loss": 379.9792175292969,
      "actor_loss": -4.235888957977295
    },
    {
      "epoch": 93,
      "value_loss": 0.09352654218673706,
      "q_loss": 380.23004150390625,
      "actor_loss": -4.227486610412598
    },
    {
      "epoch": 94,
      "value_loss": 0.08285367488861084,
      "q_loss": 380.15423583984375,
      "actor_loss": -4.234816551208496
    },
    {
      "epoch": 95,
      "value_loss": 0.08427546918392181,
      "q_loss": 380.0960388183594,
      "actor_loss": -4.235770225524902
    },
    {
      "epoch": 96,
      "value_loss": 0.0871908962726593,
      "q_loss": 380.04193115234375,
      "actor_loss": -4.2368879318237305
    },
    {
      "epoch": 97,
      "value_loss": 0.08712837845087051,
      "q_loss": 380.262939453125,
      "actor_loss": -4.236242294311523
    },
    {
      "epoch": 98,
      "value_loss": 0.08574378490447998,
      "q_loss": 380.1954040527344,
      "actor_loss": -4.237778186798096
    },
    {
      "epoch": 99,
      "value_loss": 0.0861426442861557,
      "q_loss": 380.4043273925781,
      "actor_loss": -4.234888076782227
    },
    {
      "epoch": 100,
      "value_loss": 0.08247747272253036,
      "q_loss": 380.2397155761719,
      "actor_loss": -4.238400936126709
    }
  ]
}