{
  "env": "ant-medium-v2",
  "method": "disentangled_dcor",
  "seed": 2,
  "noise_dim": 56,
  "noise_scale": 1.5,
  "noise_type": "nonlinear",
  "avg_return": 1929.0419387900251,
  "std_return": 1205.7409893843374,
  "normalized_score": 53.614294789670765,
  "latent_dim": 166,
  "pretrain_epochs": 50,
  "iql_epochs": 100,
  "encoder_checkpoint": "/home/compute/wyuhan/robust-offline-rl-disentanglement/artifacts/checkpoints/disentangled_dcor/ant-medium-v2/nd56_ns1p5_nonlinear/seed_2/encoder_epoch_50.pth",
  "obs_stats_path": "/home/compute/wyuhan/robust-offline-rl-disentanglement/artifacts/obs_stats/disentangled_dcor/ant-medium-v2/nd56_ns1p5_nonlinear/seed_2/obs_stats.npz",
  "iql_history": [
    {
      "epoch": 1,
      "value_loss": 0.02848753333091736,
      "q_loss": 7.9278244972229,
      "actor_loss": -2.9202322959899902
    },
    {
      "epoch": 2,
      "value_loss": 0.12760011851787567,
      "q_loss": 28.704296112060547,
      "actor_loss": -3.891207218170166
    },
    {
      "epoch": 3,
      "value_loss": 0.24114105105400085,
      "q_loss": 57.01715850830078,
      "actor_loss": -4.117184162139893
    },
    {
      "epoch": 4,
      "value_loss": 0.3272073566913605,
      "q_loss": 85.40442657470703,
      "actor_loss": -4.235841274261475
    },
    {
      "epoch": 5,
      "value_loss": 0.37151265144348145,
      "q_loss": 112.78555297851562,
      "actor_loss": -4.309846878051758
    },
    {
      "epoch": 6,
      "value_loss": 0.3723770081996918,
      "q_loss": 134.6709747314453,
      "actor_loss": -4.361465930938721
    },
    {
      "epoch": 7,
      "value_loss": 0.3375346064567566,
      "q_loss": 154.9668731689453,
      "actor_loss": -4.402047157287598
    },
    {
      "epoch": 8,
      "value_loss": 0.3029504418373108,
      "q_loss": 171.2424774169922,
      "actor_loss": -4.435292720794678
    },
    {
      "epoch": 9,
      "value_loss": 0.27161720395088196,
      "q_loss": 185.83836364746094,
      "actor_loss": -4.462428569793701
    },
    {
      "epoch": 10,
      "value_loss": 0.2417103499174118,
      "q_loss": 198.68557739257812,
      "actor_loss": -4.485981464385986
    },
    {
      "epoch": 11,
      "value_loss": 0.2271488606929779,
      "q_loss": 209.1516571044922,
      "actor_loss": -4.506533622741699
    },
    {
      "epoch": 12,
      "value_loss": 0.20489509403705597,
      "q_loss": 218.57530212402344,
      "actor_loss": -4.5236616134643555
    },
    {
      "epoch": 13,
      "value_loss": 0.20047332346439362,
      "q_loss": 226.90382385253906,
      "actor_loss": -4.539425373077393
    },
    {
      "epoch": 14,
      "value_loss": 0.20035365223884583,
      "q_loss": 233.30030822753906,
      "actor_loss": -4.552131175994873
    },
    {
      "epoch": 15,
      "value_loss": 0.18223610520362854,
      "q_loss": 238.55783081054688,
      "actor_loss": -4.565359115600586
    },
    {
      "epoch": 16,
      "value_loss": 0.1783667951822281,
      "q_loss": 242.50930786132812,
      "actor_loss": -4.575876712799072
    },
    {
      "epoch": 17,
      "value_loss": 0.18031525611877441,
      "q_loss": 246.7688446044922,
      "actor_loss": -4.586489677429199
    },
    {
      "epoch": 18,
      "value_loss": 0.17070940136909485,
      "q_loss": 249.44850158691406,
      "actor_loss": -4.598104476928711
    },
    {
      "epoch": 19,
      "value_loss": 0.17557677626609802,
      "q_loss": 252.1437225341797,
      "actor_loss": -4.603387832641602
    },
    {
      "epoch": 20,
      "value_loss": 0.15930452942848206,
      "q_loss": 253.84066772460938,
      "actor_loss": -4.611562252044678
    },
    {
      "epoch": 21,
      "value_loss": 0.15892797708511353,
      "q_loss": 256.3484191894531,
      "actor_loss": -4.619668006896973
    },
    {
      "epoch": 22,
      "value_loss": 0.16090638935565948,
      "q_loss": 257.54608154296875,
      "actor_loss": -4.626367092132568
    },
    {
      "epoch": 23,
      "value_loss": 0.15272784233093262,
      "q_loss": 258.6966247558594,
      "actor_loss": -4.632491111755371
    },
    {
      "epoch": 24,
      "value_loss": 0.15667422115802765,
      "q_loss": 259.9897766113281,
      "actor_loss": -4.639375686645508
    },
    {
      "epoch": 25,
      "value_loss": 0.1510894000530243,
      "q_loss": 260.7708435058594,
      "actor_loss": -4.644344329833984
    },
    {
      "epoch": 26,
      "value_loss": 0.1568334996700287,
      "q_loss": 260.7655944824219,
      "actor_loss": -4.65084171295166
    },
    {
      "epoch": 27,
      "value_loss": 0.1459871530532837,
      "q_loss": 261.3693542480469,
      "actor_loss": -4.656291961669922
    },
    {
      "epoch": 28,
      "value_loss": 0.1518523395061493,
      "q_loss": 262.1682434082031,
      "actor_loss": -4.6612114906311035
    },
    {
      "epoch": 29,
      "value_loss": 0.1441458761692047,
      "q_loss": 262.207763671875,
      "actor_loss": -4.664124011993408
    },
    {
      "epoch": 30,
      "value_loss": 0.14766757190227509,
      "q_loss": 262.9442138671875,
      "actor_loss": -4.669926166534424
    },
    {
      "epoch": 31,
      "value_loss": 0.13641539216041565,
      "q_loss": 262.76654052734375,
      "actor_loss": -4.674938201904297
    },
    {
      "epoch": 32,
      "value_loss": 0.13392984867095947,
      "q_loss": 263.2353210449219,
      "actor_loss": -4.677517414093018
    },
    {
      "epoch": 33,
      "value_loss": 0.1496734470129013,
      "q_loss": 263.51385498046875,
      "actor_loss": -4.681309700012207
    },
    {
      "epoch": 34,
      "value_loss": 0.13001090288162231,
      "q_loss": 263.3984375,
      "actor_loss": -4.685091972351074
    },
    {
      "epoch": 35,
      "value_loss": 0.1344965249300003,
      "q_loss": 263.76751708984375,
      "actor_loss": -4.688404083251953
    },
    {
      "epoch": 36,
      "value_loss": 0.1329023540019989,
      "q_loss": 263.8722229003906,
      "actor_loss": -4.691422462463379
    },
    {
      "epoch": 37,
      "value_loss": 0.14787212014198303,
      "q_loss": 263.97430419921875,
      "actor_loss": -4.694941520690918
    },
    {
      "epoch": 38,
      "value_loss": 0.11903960257768631,
      "q_loss": 263.680419921875,
      "actor_loss": -4.698737144470215
    },
    {
      "epoch": 39,
      "value_loss": 0.15610267221927643,
      "q_loss": 263.9676513671875,
      "actor_loss": -4.699816703796387
    },
    {
      "epoch": 40,
      "value_loss": 0.1260896921157837,
      "q_loss": 263.6681213378906,
      "actor_loss": -4.70408296585083
    },
    {
      "epoch": 41,
      "value_loss": 0.12760433554649353,
      "q_loss": 263.7695007324219,
      "actor_loss": -4.707823276519775
    },
    {
      "epoch": 42,
      "value_loss": 0.13192640244960785,
      "q_loss": 264.1358947753906,
      "actor_loss": -4.709946155548096
    },
    {
      "epoch": 43,
      "value_loss": 0.11629758030176163,
      "q_loss": 264.1469421386719,
      "actor_loss": -4.712336540222168
    },
    {
      "epoch": 44,
      "value_loss": 0.1275852918624878,
      "q_loss": 264.4043884277344,
      "actor_loss": -4.714746475219727
    },
    {
      "epoch": 45,
      "value_loss": 0.13352476060390472,
      "q_loss": 264.3381042480469,
      "actor_loss": -4.71743106842041
    },
    {
      "epoch": 46,
      "value_loss": 0.12221145629882812,
      "q_loss": 264.5357971191406,
      "actor_loss": -4.720280647277832
    },
    {
      "epoch": 47,
      "value_loss": 0.12274219840765,
      "q_loss": 264.372802734375,
      "actor_loss": -4.7227654457092285
    },
    {
      "epoch": 48,
      "value_loss": 0.1092626228928566,
      "q_loss": 264.515869140625,
      "actor_loss": -4.723091125488281
    },
    {
      "epoch": 49,
      "value_loss": 0.12149126082658768,
      "q_loss": 263.9302978515625,
      "actor_loss": -4.72598934173584
    },
    {
      "epoch": 50,
      "value_loss": 0.12038975208997726,
      "q_loss": 264.2657470703125,
      "actor_loss": -4.727590560913086
    },
    {
      "epoch": 51,
      "value_loss": 0.11333827674388885,
      "q_loss": 263.9222412109375,
      "actor_loss": -4.730071544647217
    },
    {
      "epoch": 52,
      "value_loss": 0.11835991591215134,
      "q_loss": 264.4710693359375,
      "actor_loss": -4.732548713684082
    },
    {
      "epoch": 53,
      "value_loss": 0.11285661160945892,
      "q_loss": 264.4010925292969,
      "actor_loss": -4.734672546386719
    },
    {
      "epoch": 54,
      "value_loss": 0.11249174922704697,
      "q_loss": 264.4588317871094,
      "actor_loss": -4.736025333404541
    },
    {
      "epoch": 55,
      "value_loss": 0.11229780316352844,
      "q_loss": 264.14019775390625,
      "actor_loss": -4.737900257110596
    },
    {
      "epoch": 56,
      "value_loss": 0.11082467436790466,
      "q_loss": 264.7120666503906,
      "actor_loss": -4.740137577056885
    },
    {
      "epoch": 57,
      "value_loss": 0.12189798802137375,
      "q_loss": 264.28839111328125,
      "actor_loss": -4.741535663604736
    },
    {
      "epoch": 58,
      "value_loss": 0.10920735448598862,
      "q_loss": 264.245849609375,
      "actor_loss": -4.742880344390869
    },
    {
      "epoch": 59,
      "value_loss": 0.10891686379909515,
      "q_loss": 264.3424377441406,
      "actor_loss": -4.743748664855957
    },
    {
      "epoch": 60,
      "value_loss": 0.10955868661403656,
      "q_loss": 264.1963195800781,
      "actor_loss": -4.74543571472168
    },
    {
      "epoch": 61,
      "value_loss": 0.10316567867994308,
      "q_loss": 264.0584411621094,
      "actor_loss": -4.74669075012207
    },
    {
      "epoch": 62,
      "value_loss": 0.11454975605010986,
      "q_loss": 264.339599609375,
      "actor_loss": -4.748793125152588
    },
    {
      "epoch": 63,
      "value_loss": 0.11324500292539597,
      "q_loss": 264.1275329589844,
      "actor_loss": -4.749390125274658
    },
    {
      "epoch": 64,
      "value_loss": 0.1062474399805069,
      "q_loss": 263.7366027832031,
      "actor_loss": -4.750741004943848
    },
    {
      "epoch": 65,
      "value_loss": 0.10200215131044388,
      "q_loss": 264.2388610839844,
      "actor_loss": -4.7526092529296875
    },
    {
      "epoch": 66,
      "value_loss": 0.10417011380195618,
      "q_loss": 264.38018798828125,
      "actor_loss": -4.754312038421631
    },
    {
      "epoch": 67,
      "value_loss": 0.09697898477315903,
      "q_loss": 264.3572998046875,
      "actor_loss": -4.756483554840088
    },
    {
      "epoch": 68,
      "value_loss": 0.10248569399118423,
      "q_loss": 264.19482421875,
      "actor_loss": -4.75783109664917
    },
    {
      "epoch": 69,
      "value_loss": 0.10021085292100906,
      "q_loss": 264.42315673828125,
      "actor_loss": -4.75943660736084
    },
    {
      "epoch": 70,
      "value_loss": 0.1057678833603859,
      "q_loss": 263.97222900390625,
      "actor_loss": -4.758378982543945
    },
    {
      "epoch": 71,
      "value_loss": 0.10002514719963074,
      "q_loss": 264.10699462890625,
      "actor_loss": -4.760950565338135
    },
    {
      "epoch": 72,
      "value_loss": 0.10536747425794601,
      "q_loss": 264.01300048828125,
      "actor_loss": -4.760651588439941
    },
    {
      "epoch": 73,
      "value_loss": 0.11265702545642853,
      "q_loss": 264.065673828125,
      "actor_loss": -4.763004779815674
    },
    {
      "epoch": 74,
      "value_loss": 0.11234818398952484,
      "q_loss": 264.37579345703125,
      "actor_loss": -4.763123989105225
    },
    {
      "epoch": 75,
      "value_loss": 0.10746133327484131,
      "q_loss": 263.96856689453125,
      "actor_loss": -4.764995098114014
    },
    {
      "epoch": 76,
      "value_loss": 0.09257425367832184,
      "q_loss": 263.5358581542969,
      "actor_loss": -4.765523910522461
    },
    {
      "epoch": 77,
      "value_loss": 0.09084063768386841,
      "q_loss": 264.01898193359375,
      "actor_loss": -4.7679033279418945
    },
    {
      "epoch": 78,
      "value_loss": 0.09973225742578506,
      "q_loss": 264.1771545410156,
      "actor_loss": -4.7682037353515625
    },
    {
      "epoch": 79,
      "value_loss": 0.09572353214025497,
      "q_loss": 263.5912170410156,
      "actor_loss": -4.769597053527832
    },
    {
      "epoch": 80,
      "value_loss": 0.10164617747068405,
      "q_loss": 263.88714599609375,
      "actor_loss": -4.770831108093262
    },
    {
      "epoch": 81,
      "value_loss": 0.11239425092935562,
      "q_loss": 264.0536193847656,
      "actor_loss": -4.7710418701171875
    },
    {
      "epoch": 82,
      "value_loss": 0.07766754180192947,
      "q_loss": 263.7458190917969,
      "actor_loss": -4.772716045379639
    },
    {
      "epoch": 83,
      "value_loss": 0.09598356485366821,
      "q_loss": 263.57843017578125,
      "actor_loss": -4.773763179779053
    },
    {
      "epoch": 84,
      "value_loss": 0.09342897683382034,
      "q_loss": 263.3609924316406,
      "actor_loss": -4.77373743057251
    },
    {
      "epoch": 85,
      "value_loss": 0.09507657587528229,
      "q_loss": 263.9395751953125,
      "actor_loss": -4.775277614593506
    },
    {
      "epoch": 86,
      "value_loss": 0.0943116769194603,
      "q_loss": 263.4847106933594,
      "actor_loss": -4.775579452514648
    },
    {
      "epoch": 87,
      "value_loss": 0.09367963671684265,
      "q_loss": 263.4608154296875,
      "actor_loss": -4.776593208312988
    },
    {
      "epoch": 88,
      "value_loss": 0.0858679860830307,
      "q_loss": 263.5791320800781,
      "actor_loss": -4.777703285217285
    },
    {
      "epoch": 89,
      "value_loss": 0.08643808215856552,
      "q_loss": 263.4831237792969,
      "actor_loss": -4.779504299163818
    },
    {
      "epoch": 90,
      "value_loss": 0.09046845883131027,
      "q_loss": 263.8509521484375,
      "actor_loss": -4.77908182144165
    },
    {
      "epoch": 91,
      "value_loss": 0.08627573400735855,
      "q_loss": 263.9686584472656,
      "actor_loss": -4.7808661460876465
    },
    {
      "epoch": 92,
      "value_loss": 0.09002135694026947,
      "q_loss": 263.8213195800781,
      "actor_loss": -4.781120777130127
    },
    {
      "epoch": 93,
      "value_loss": 0.08881713449954987,
      "q_loss": 263.6656799316406,
      "actor_loss": -4.780564785003662
    },
    {
      "epoch": 94,
      "value_loss": 0.09414201229810715,
      "q_loss": 263.8155212402344,
      "actor_loss": -4.782749176025391
    },
    {
      "epoch": 95,
      "value_loss": 0.08798270672559738,
      "q_loss": 263.6472473144531,
      "actor_loss": -4.7833781242370605
    },
    {
      "epoch": 96,
      "value_loss": 0.07980351150035858,
      "q_loss": 263.21435546875,
      "actor_loss": -4.783947944641113
    },
    {
      "epoch": 97,
      "value_loss": 0.08451129496097565,
      "q_loss": 263.6390075683594,
      "actor_loss": -4.786181449890137
    },
    {
      "epoch": 98,
      "value_loss": 0.11504204571247101,
      "q_loss": 263.9154052734375,
      "actor_loss": -4.785055637359619
    },
    {
      "epoch": 99,
      "value_loss": 0.07501784712076187,
      "q_loss": 263.2988586425781,
      "actor_loss": -4.786018371582031
    },
    {
      "epoch": 100,
      "value_loss": 0.08381130546331406,
      "q_loss": 263.7372741699219,
      "actor_loss": -4.786585330963135
    }
  ]
}